self_rewarding_lm_pytorch/__init__.py
self_rewarding_lm_pytorch/dpo.py
self_rewarding_lm_pytorch/mocks.py
self_rewarding_lm_pytorch/sampling_utils.py
self_rewarding_lm_pytorch/self_rewarding_lm_pytorch.py
self_rewarding_lm_pytorch/spin.py
self_rewarding_lm_pytorch-0.2.12.dist-info/LICENSE
self_rewarding_lm_pytorch-0.2.12.dist-info/METADATA
self_rewarding_lm_pytorch-0.2.12.dist-info/WHEEL
self_rewarding_lm_pytorch-0.2.12.dist-info/top_level.txt
self_rewarding_lm_pytorch-0.2.12.dist-info/RECORD
