Metadata-Version: 2.1
Name: self-rewarding-lm-pytorch
Version: 0.2.12
Summary: Self Rewarding LM - Pytorch
Home-page: https://github.com/lucidrains/self-rewarding-lm-pytorch
Author: Phil Wang
Author-email: lucidrains@gmail.com
License: MIT
Keywords: artificial intelligence,deep learning,self rewarding,direct preference optimization
Classifier: Development Status :: 4 - Beta
Classifier: Intended Audience :: Developers
Classifier: Topic :: Scientific/Engineering :: Artificial Intelligence
Classifier: License :: OSI Approved :: MIT License
Classifier: Programming Language :: Python :: 3.6
License-File: LICENSE
Requires-Dist: accelerate
Requires-Dist: beartype
Requires-Dist: einops >=0.7.0
Requires-Dist: einx[torch] >=0.1.3
Requires-Dist: ema-pytorch >=0.3.3
Requires-Dist: Jinja2
Requires-Dist: numpy
Requires-Dist: pytorch-custom-utils >=0.0.17
Requires-Dist: torch >=2.0
Requires-Dist: torchtyping
Requires-Dist: tqdm
